[{"city":"Minneapolis","incident_hour":0,"average_response_time":8.999304743339831,"median_response_time":6.9,"average_call_time":3.748011695906433,"median_call_time":2.7,"average_to_queue_time":1.4298960363872646,"median_to_queue_time":1.1,"average_in_queue_time":2.2510526315789474,"median_in_queue_time":0.6166666666666667,"average_drive_time":5.318356075373619,"median_drive_time":4.15,"incidents":"2565"},{"city":"Minneapolis","incident_hour":1,"average_response_time":8.295931869369369,"median_response_time":6.366666666666667,"average_call_time":3.871199324324324,"median_call_time":2.75,"average_to_queue_time":1.4566230292792792,"median_to_queue_time":1.0833333333333333,"average_in_queue_time":1.8680813626126127,"median_in_queue_time":0.5833333333333334,"average_drive_time":4.971227477477478,"median_drive_time":3.8833333333333333,"incidents":"2368"},{"city":"Minneapolis","incident_hour":2,"average_response_time":7.852957423874966,"median_response_time":5.758333333333333,"average_call_time":3.626775845801321,"median_call_time":2.6666666666666665,"average_to_queue_time":1.4076964550478501,"median_to_queue_time":1.05,"average_in_queue_time":2.3517448127189438,"median_in_queue_time":0.65,"average_drive_time":4.094085152250067,"median_drive_time":3.183333333333333,"incidents":"2474"},{"city":"Minneapolis","incident_hour":3,"average_response_time":8.407928531546622,"median_response_time":6.45,"average_call_time":4.026391215335939,"median_call_time":2.8,"average_to_queue_time":1.4573329611018053,"median_to_queue_time":1.0833333333333333,"average_in_queue_time":2.2545133072771266,"median_in_queue_time":0.6166666666666667,"average_drive_time":4.69608226316769,"median_drive_time":3.75,"incidents":"1791"},{"city":"Minneapolis","incident_hour":4,"average_response_time":8.588480779357557,"median_response_time":6.75,"average_call_time":4.0248484848484845,"median_call_time":2.6,"average_to_queue_time":1.3683794466403163,"median_to_queue_time":1.0833333333333333,"average_in_queue_time":2.3102817272248553,"median_in_queue_time":0.6,"average_drive_time":4.9109004739336495,"median_drive_time":4.033333333333333,"incidents":"1266"},{"city":"Minneapolis","incident_hour":5,"average_response_time":9.6554325361677,"median_response_time":7.016666666666667,"average_call_time":3.876764098021848,"median_call_time":2.65,"average_to_queue_time":1.4449217596693238,"median_to_queue_time":1.15,"average_in_queue_time":2.9010628875110718,"median_in_queue_time":0.5166666666666667,"average_drive_time":5.309447888987305,"median_drive_time":4.6,"incidents":"1129"},{"city":"Minneapolis","incident_hour":6,"average_response_time":24.26695,"median_response_time":16.75,"average_call_time":3.372706039372706,"median_call_time":2.3,"average_to_queue_time":1.504788121454788,"median_to_queue_time":1.2,"average_in_queue_time":15.831066666666667,"median_in_queue_time":7.108333333333333,"average_drive_time":6.9326,"median_drive_time":5.383333333333333,"incidents":"1000"},{"city":"Minneapolis","incident_hour":7,"average_response_time":12.372385500857213,"median_response_time":9.866666666666667,"average_call_time":3.271442566740142,"median_call_time":2.316666666666667,"average_to_queue_time":1.522642664707323,"median_to_queue_time":1.1833333333333333,"average_in_queue_time":2.992223855008572,"median_in_queue_time":0.6833333333333333,"average_drive_time":7.857518981141317,"median_drive_time":6.466666666666667,"incidents":"1361"},{"city":"Minneapolis","incident_hour":8,"average_response_time":11.18544921875,"median_response_time":9.466666666666667,"average_call_time":3.0399739583333334,"median_call_time":2.2333333333333334,"average_to_queue_time":1.5346788194444445,"median_to_queue_time":1.1833333333333333,"average_in_queue_time":1.8410807291666667,"median_in_queue_time":0.6666666666666666,"average_drive_time":7.809689670138889,"median_drive_time":6.533333333333333,"incidents":"1536"},{"city":"Minneapolis","incident_hour":9,"average_response_time":11.187249114521842,"median_response_time":8.983333333333333,"average_call_time":3.0412534435261707,"median_call_time":2.2666666666666666,"average_to_queue_time":1.498780007870917,"median_to_queue_time":1.1333333333333333,"average_in_queue_time":2.256090121999213,"median_in_queue_time":0.7166666666666667,"average_drive_time":7.432378984651712,"median_drive_time":5.95,"incidents":"1694"},{"city":"Minneapolis","incident_hour":10,"average_response_time":10.974345597656965,"median_response_time":8.633333333333333,"average_call_time":3.1226249313563974,"median_call_time":2.45,"average_to_queue_time":1.554329123192385,"median_to_queue_time":1.2,"average_in_queue_time":2.587634999084752,"median_in_queue_time":0.75,"average_drive_time":6.832381475379828,"median_drive_time":5.583333333333333,"incidents":"1821"},{"city":"Minneapolis","incident_hour":11,"average_response_time":11.90105610561056,"median_response_time":9.033333333333333,"average_call_time":3.1899422442244223,"median_call_time":2.45,"average_to_queue_time":1.5616501650165018,"median_to_queue_time":1.2333333333333334,"average_in_queue_time":3.41233498349835,"median_in_queue_time":0.85,"average_drive_time":6.92707095709571,"median_drive_time":5.758333333333333,"incidents":"2020"},{"city":"Minneapolis","incident_hour":12,"average_response_time":12.094338670128371,"median_response_time":9.4,"average_call_time":3.216219336219336,"median_call_time":2.4916666666666667,"average_to_queue_time":1.593088023088023,"median_to_queue_time":1.2,"average_in_queue_time":3.427217654694937,"median_in_queue_time":0.9666666666666667,"average_drive_time":7.0747223424203085,"median_drive_time":5.716666666666667,"incidents":"2311"},{"city":"Minneapolis","incident_hour":13,"average_response_time":11.908750684181719,"median_response_time":9.183333333333334,"average_call_time":3.160727969348659,"median_call_time":2.4833333333333334,"average_to_queue_time":1.56042008757526,"median_to_queue_time":1.2166666666666668,"average_in_queue_time":3.415524083196497,"median_in_queue_time":0.9,"average_drive_time":6.932806513409962,"median_drive_time":5.466666666666667,"incidents":"2436"},{"city":"Minneapolis","incident_hour":14,"average_response_time":11.607426900584795,"median_response_time":8.9,"average_call_time":3.223482781026641,"median_call_time":2.6,"average_to_queue_time":1.5342040285899936,"median_to_queue_time":1.1833333333333333,"average_in_queue_time":3.4911890838206627,"median_in_queue_time":0.8666666666666667,"average_drive_time":6.582033788174139,"median_drive_time":5.45,"incidents":"2565"},{"city":"Minneapolis","incident_hour":15,"average_response_time":13.951383077638308,"median_response_time":8.941666666666666,"average_call_time":3.5004823337982334,"median_call_time":2.7666666666666666,"average_to_queue_time":1.5619014411901442,"median_to_queue_time":1.15,"average_in_queue_time":5.791777080427708,"median_in_queue_time":0.9833333333333333,"average_drive_time":6.597704556020456,"median_drive_time":5.183333333333334,"incidents":"2868"},{"city":"Minneapolis","incident_hour":16,"average_response_time":13.88531129476584,"median_response_time":9.783333333333333,"average_call_time":3.3596914600550964,"median_call_time":2.65,"average_to_queue_time":1.556396694214876,"median_to_queue_time":1.1833333333333333,"average_in_queue_time":5.285074380165289,"median_in_queue_time":1.0666666666666667,"average_drive_time":7.0438402203856745,"median_drive_time":5.466666666666667,"incidents":"3025"},{"city":"Minneapolis","incident_hour":17,"average_response_time":10.898307533539732,"median_response_time":8.45,"average_call_time":3.3251186790505676,"median_call_time":2.6666666666666665,"average_to_queue_time":1.5136687306501548,"median_to_queue_time":1.1666666666666667,"average_in_queue_time":2.8967698658410734,"median_in_queue_time":0.7833333333333333,"average_drive_time":6.487868937048503,"median_drive_time":5.166666666666667,"incidents":"3230"},{"city":"Minneapolis","incident_hour":18,"average_response_time":10.366651282051283,"median_response_time":8.166666666666666,"average_call_time":3.3476,"median_call_time":2.6666666666666665,"average_to_queue_time":1.4615384615384615,"median_to_queue_time":1.1333333333333333,"average_in_queue_time":2.7459589743589743,"median_in_queue_time":0.7833333333333333,"average_drive_time":6.159153846153846,"median_drive_time":4.85,"incidents":"3250"},{"city":"Minneapolis","incident_hour":19,"average_response_time":10.178475500996747,"median_response_time":7.666666666666667,"average_call_time":3.4753096137699413,"median_call_time":2.65,"average_to_queue_time":1.4675430310663309,"median_to_queue_time":1.0833333333333333,"average_in_queue_time":2.9936155702444656,"median_in_queue_time":0.7833333333333333,"average_drive_time":5.717778826985626,"median_drive_time":4.533333333333333,"incidents":"3177"},{"city":"Minneapolis","incident_hour":20,"average_response_time":10.435450944546009,"median_response_time":7.883333333333333,"average_call_time":3.3839124250736563,"median_call_time":2.65,"average_to_queue_time":1.4864167428629482,"median_to_queue_time":1.1333333333333333,"average_in_queue_time":3.3169358114970544,"median_in_queue_time":0.7833333333333333,"average_drive_time":5.632551289863904,"median_drive_time":4.566666666666666,"incidents":"3282"},{"city":"Minneapolis","incident_hour":21,"average_response_time":8.733464012866907,"median_response_time":6.733333333333333,"average_call_time":3.440978086047447,"median_call_time":2.6666666666666665,"average_to_queue_time":1.4966224366706875,"median_to_queue_time":1.15,"average_in_queue_time":2.1167973462002414,"median_in_queue_time":0.6333333333333333,"average_drive_time":5.120044229995979,"median_drive_time":4.058333333333334,"incidents":"3316"},{"city":"Minneapolis","incident_hour":22,"average_response_time":8.02722121028132,"median_response_time":6.266666666666667,"average_call_time":3.4146124266342848,"median_call_time":2.625,"average_to_queue_time":1.474605343047966,"median_to_queue_time":1.1,"average_in_queue_time":1.444575996761789,"median_in_queue_time":0.5666666666666667,"average_drive_time":5.108039870471565,"median_drive_time":3.966666666666667,"incidents":"3294"},{"city":"Minneapolis","incident_hour":23,"average_response_time":8.00091877340824,"median_response_time":6.333333333333333,"average_call_time":3.800866104868914,"median_call_time":2.783333333333333,"average_to_queue_time":1.4607736423220974,"median_to_queue_time":1.1,"average_in_queue_time":1.578002106741573,"median_in_queue_time":0.5666666666666667,"average_drive_time":4.962143024344569,"median_drive_time":3.8833333333333333,"incidents":"2848"}]
